cal_ai/__init__.py
cal_ai/ai_monitor.py
cal_ai/cal_crawler.py
cal_ai/cal_plot.py
cal_ai/common_utils.py
cal_ai/daily_checker.py
cal_ai/data_template.py
cal_ai/healthy_checker.py
cal_ai-0.2.0.9.dist-info/DESCRIPTION.rst
cal_ai-0.2.0.9.dist-info/METADATA
cal_ai-0.2.0.9.dist-info/RECORD
cal_ai-0.2.0.9.dist-info/WHEEL
cal_ai-0.2.0.9.dist-info/metadata.json
cal_ai-0.2.0.9.dist-info/top_level.txt
