Metadata-Version: 2.0
Name: cal-ai
Version: 0.2.0.9
Summary: An end-to-end machine learning and data mining framework on Hadoop CAL.
Home-page: https://github.paypal.com/haifwu/LiveBoxMonitor
Author: Wu Haifeng
Author-email: wuhaifengdhu@163.com
License: UNKNOWN
Platform: UNKNOWN
Classifier: License :: OSI Approved :: MIT License
Classifier: Operating System :: OS Independent
Classifier: Natural Language :: English
Classifier: Programming Language :: Python
Classifier: Programming Language :: Python :: 2
Classifier: Programming Language :: Python :: 2.6
Classifier: Programming Language :: Python :: 2.7
Classifier: Programming Language :: Python :: 3
Classifier: Programming Language :: Python :: 3.2
Classifier: Programming Language :: Python :: 3.3
Classifier: Programming Language :: Python :: 3.4
Classifier: Programming Language :: Python :: 3.5
Classifier: Programming Language :: Python :: 3.6
Classifier: Programming Language :: Python :: 3.7
Requires-Dist: matplotlib
Requires-Dist: numpy
Requires-Dist: pandas
